odoo/addons/purchase_report_payment_term/README.rst
odoo/addons/purchase_report_payment_term/__init__.py
odoo/addons/purchase_report_payment_term/__manifest__.py
odoo/addons/purchase_report_payment_term/i18n/it.po
odoo/addons/purchase_report_payment_term/i18n/pt_BR.po
odoo/addons/purchase_report_payment_term/i18n/purchase_report_payment_term.pot
odoo/addons/purchase_report_payment_term/readme/CONTRIBUTORS.md
odoo/addons/purchase_report_payment_term/readme/DESCRIPTION.md
odoo/addons/purchase_report_payment_term/reports/purchase_order_templates.xml
odoo/addons/purchase_report_payment_term/reports/purchase_quotation_templates.xml
odoo/addons/purchase_report_payment_term/static/description/icon.png
odoo/addons/purchase_report_payment_term/static/description/index.html
odoo_addon_purchase_report_payment_term-17.0.1.0.0.2.dist-info/METADATA
odoo_addon_purchase_report_payment_term-17.0.1.0.0.2.dist-info/WHEEL
odoo_addon_purchase_report_payment_term-17.0.1.0.0.2.dist-info/top_level.txt
odoo_addon_purchase_report_payment_term-17.0.1.0.0.2.dist-info/RECORD
