Metadata-Version: 2.1
Name: odoo-addon-purchase_report_payment_term
Version: 17.0.1.0.0.2
Requires-Python: >=3.10
Requires-Dist: odoo>=17.0a,<17.1dev
Summary: Purchase Report Payment Term
Home-page: https://github.com/OCA/purchase-reporting
License: AGPL-3
Author: Quartile Limited, Odoo Community Association (OCA)
Author-email: support@odoo-community.org
Classifier: Programming Language :: Python
Classifier: Framework :: Odoo
Classifier: Framework :: Odoo :: 17.0
Classifier: License :: OSI Approved :: GNU Affero General Public License v3
